weibo/__init__.py
weibo/cli.py
weibo/client.py
weibo/helper
weibo/log.py
weibo_sofa-0.1.8.dist-info/DESCRIPTION.rst
weibo_sofa-0.1.8.dist-info/METADATA
weibo_sofa-0.1.8.dist-info/RECORD
weibo_sofa-0.1.8.dist-info/WHEEL
weibo_sofa-0.1.8.dist-info/entry_points.txt
weibo_sofa-0.1.8.dist-info/metadata.json
weibo_sofa-0.1.8.dist-info/top_level.txt
