Metadata-Version: 2.0
Name: weibo-sofa
Version: 0.1.8
Summary: Auto-grab sina weibo sofa
Home-page: UNKNOWN
Author: wisecsj
Author-email: wisecsj@gamil.com
License: UNKNOWN
Keywords: sina weibo sofa python
Platform: UNKNOWN
Requires-Python: >=3
Requires-Dist: Pillow
Requires-Dist: requests
Requires-Dist: rsa
